odoo8_addon_l10n_ar_account_create_check-8.0.0.1.0.99.dev3-py2.7-nspkg.pth
odoo8_addon_l10n_ar_account_create_check-8.0.0.1.0.99.dev3.dist-info/METADATA
odoo8_addon_l10n_ar_account_create_check-8.0.0.1.0.99.dev3.dist-info/RECORD
odoo8_addon_l10n_ar_account_create_check-8.0.0.1.0.99.dev3.dist-info/WHEEL
odoo8_addon_l10n_ar_account_create_check-8.0.0.1.0.99.dev3.dist-info/namespace_packages.txt
odoo8_addon_l10n_ar_account_create_check-8.0.0.1.0.99.dev3.dist-info/top_level.txt
odoo_addons/l10n_ar_account_create_check/.gitignore
odoo_addons/l10n_ar_account_create_check/AUTHORS
odoo_addons/l10n_ar_account_create_check/__init__.py
odoo_addons/l10n_ar_account_create_check/__openerp__.py
odoo_addons/l10n_ar_account_create_check/account_voucher_view.xml
odoo_addons/l10n_ar_account_create_check/checkbook.py
odoo_addons/l10n_ar_account_create_check/checkbook_view.xml
odoo_addons/l10n_ar_account_create_check/i18n/es.po
odoo_addons/l10n_ar_account_create_check/i18n/es_AR.po
odoo_addons/l10n_ar_account_create_check/security/ir.model.access.csv
odoo_addons/l10n_ar_account_create_check/static/description/icon.png
odoo_addons/l10n_ar_account_create_check/wizard/__init__.py
odoo_addons/l10n_ar_account_create_check/wizard/create_checkbook.py
odoo_addons/l10n_ar_account_create_check/wizard/create_checkbook_view.xml
