Metadata-Version: 2.1
Name: odoo8-addon-l10n-ar-account-create-check
Version: 8.0.0.1.0.99.dev3
Summary: Checkbook Management
Home-page: http://eynes.com.ar/
Author: eynes.com.ar,Odoo Community Association (OCA)
Author-email: support@odoo-community.org
License: AGPL-3
Platform: UNKNOWN
Classifier: Programming Language :: Python
Classifier: Framework :: Odoo
Classifier: License :: OSI Approved :: GNU Affero General Public License v3
Requires-Python: ~=2.7
Requires-Dist: odoo8-addon-l10n-ar-account-check
Requires-Dist: odoo (<9.0a,>=8.0a)
